llama_index/llms/openllm/__init__.py
llama_index/llms/openllm/base.py
llama_index_llms_openllm-0.4.2.dist-info/METADATA
llama_index_llms_openllm-0.4.2.dist-info/WHEEL
llama_index_llms_openllm-0.4.2.dist-info/licenses/LICENSE
llama_index_llms_openllm-0.4.2.dist-info/RECORD
