Metadata-Version: 2.4
Name: llama-index-llms-openllm
Version: 0.4.2
Summary: llama-index llms openllm integration
Author-email: Aaron Pham <aarnphm@bentoml.com>
License-Expression: MIT
License-File: LICENSE
Requires-Python: <4.0,>=3.9
Requires-Dist: llama-index-core<0.13,>=0.12.0
Requires-Dist: llama-index-llms-openai-like<0.5,>=0.4.0
Requires-Dist: openllm>=0.6.0
